{"title": "Apasu Enawa \u2013 \u0d86\u0db4\u0dc3\u0dd4 \u0d91\u0db1\u0dc0\u0dcf", "views": 4193, "Genre": " Old Pops", "Artist": " Priya Sooriyasena", "Lyrics": " Daya De Alwis", "Music": " Priya Sooriyasena", "song_lyrics": "\u0d86\u0db4\u0dc3\u0dd4 \u0d91\u0db1\u0dc0\u0dcf \u0db8\u0d9c\u0dda \u0dc4\u0dd2\u0dad \u0d89\u0db6\u0dd2 \u0d9c\u0db8\u0db1\u0dd2\u0db1\u0dca\n\u0d94\u0db6 \u0d88\u0dad\u0d9a \u0dbb\u0db3\u0dc0\u0dcf\n\u0d9a\u0dcf\u0da7 \u0d9a\u0dd2\u0dba\u0db8\u0dca\u0daf\u0ddd \u0d9a\u0dd9\u0dbd\u0dd9\u0dc3 \u0d9a\u0dd2\u0dba\u0db1\u0dca\u0db1\u0daf \u0db8\u0d82\n\u0d85\u0db4 \u0dc3\u0dd2\u0dad\u0dca \u0dc4\u0dac\u0db1 \u0dad\u0dbb\u0db8\u0dca\n                           \t \n\u0d94\u0db6 \u0db1\u0dd0\u0dc0\u0dad\u0dd4\u0db1 \u0dad\u0dd0\u0db1 \u0db8\u0d9c\u0dda \u0dc4\u0dd2\u0dad \u200d\u0d94\u0db6\u0dd9 \u0dc5\u0d9f\n\u0dc0\u0dd9\u0db1\u0dad\u0d9a \u0db1\u0dd0\u0dad\u0dda \u0dbd\u0dd0\u0d9c\u0dd4\u0db8\u0dca \n\u0d9a\u0dc0\u0dd4\u0dbb\u0dd4 \u0daf\u0d9a\u0dd2\u0db1\u0dca\u0db1\u0daf \u0d9a\u0dd9\u0dbd\u0dd9\u0dc3 \u0db4\u0dad\u0db1\u0dca\u0db1\u0daf\n\u0d85\u0daf \u0db8\u0dcf \u0dc4\u0dd9\u0dbd\u0db1 \u0dc3\u0dd4\u0dc3\u0dd4\u0db8\u0dca\n                         \t \n\u0d89\u0dc4\u0da7 \u0dc0\u0dc4\u0dbd \u0dc3\u0dda \u0dad\u0dbb\u0dd4 \u0db4\u0dd2\u0dbb\u0dd2 \u0d85\u0dc4\u0dc3\u0dda\n\u0db1\u0dd2\u0dc0\u0dc4\u0db1 \u0dc0\u0dd6 \u0db4\u0ddc\u0dc5\u0dc0\u0dba\u0dd2 \n\u0dc4\u0db8\u0dd4\u0dc0\u0dd6 \u0dad\u0dd0\u0db1\u0dca \u0dc0\u0dbd \u0d9c\u0dc3\u0dca \u0dc0\u0dd0\u0dbd\u0dca \u0dc0\u0dd0\u0dc5\u0db4\u0dd9\u0dba\u0dd2\n\u0db1\u0ddc\u0dc4\u0dac\u0db8\u0dd4 \u0d94\u0db6\u0dba\u0dd2 \u0db8\u0db8\u0dba\u0dd2\n"}